flet_easy_static/__init__.py
flet_easy_static/auto_route.py
flet_easy_static/datasy.py
flet_easy_static/extra.py
flet_easy_static/extrasJwt.py
flet_easy_static/fletEasy.py
flet_easy_static/inheritance.py
flet_easy_static/job.py
flet_easy_static/jwt.py
flet_easy_static/pagesy.py
flet_easy_static/route.py
flet_easy_static/view_404.py
flet_easy_static-0.2.6.dist-info/METADATA
flet_easy_static-0.2.6.dist-info/WHEEL
flet_easy_static-0.2.6.dist-info/top_level.txt
flet_easy_static-0.2.6.dist-info/RECORD
