Metadata-Version: 2.1
Name: flet-easy-static
Version: 0.2.6
Requires-Dist: PyJWT
Requires-Dist: rsa
Requires-Dist: parse
Requires-Dist: ssl
